voiceground/__init__.py
voiceground/evaluator.py
voiceground/events.py
voiceground/metrics.py
voiceground/observer.py
voiceground/py.typed
voiceground/_static/index.html
voiceground/evaluations/__init__.py
voiceground/evaluations/base.py
voiceground/evaluations/providers/__init__.py
voiceground/evaluations/providers/openai.py
voiceground/reporters/__init__.py
voiceground/reporters/base.py
voiceground/reporters/html.py
voiceground/reporters/metrics.py
voiceground/reporters/summary.py
voiceground/simulation/__init__.py
voiceground/simulation/bridge.py
voiceground/simulation/config.py
voiceground/simulation/runner.py
voiceground-0.1.6.dist-info/METADATA
voiceground-0.1.6.dist-info/WHEEL
voiceground-0.1.6.dist-info/licenses/LICENSE
voiceground-0.1.6.dist-info/RECORD
