Metadata-Version: 2.4
Name: voiceground
Version: 0.1.6
Summary: Observability framework for Pipecat voice and multimodal conversational AI
Project-URL: Homepage, https://github.com/poseneror/voiceground
Project-URL: Documentation, https://github.com/poseneror/voiceground#readme
Project-URL: Repository, https://github.com/poseneror/voiceground
Project-URL: Issues, https://github.com/poseneror/voiceground/issues
Author-email: Or Posener <posener.or@gmail.com>
License-Expression: BSD-2-Clause
License-File: LICENSE
Keywords: ai,conversational-ai,observability,pipecat,real-time,voice
Classifier: Development Status :: 3 - Alpha
Classifier: Intended Audience :: Developers
Classifier: License :: OSI Approved :: BSD License
Classifier: Programming Language :: Python :: 3
Classifier: Programming Language :: Python :: 3.10
Classifier: Programming Language :: Python :: 3.11
Classifier: Programming Language :: Python :: 3.12
Classifier: Topic :: Scientific/Engineering :: Artificial Intelligence
Requires-Python: >=3.10
Requires-Dist: pipecat-ai>=0.0.99
Provides-Extra: dev
Requires-Dist: mypy>=1.0.0; extra == 'dev'
Requires-Dist: pytest-asyncio>=0.21; extra == 'dev'
Requires-Dist: pytest>=7.0; extra == 'dev'
Requires-Dist: ruff>=0.1.0; extra == 'dev'
Provides-Extra: examples
Requires-Dist: aiohttp>=3.9; extra == 'examples'
Requires-Dist: loguru>=0.7; extra == 'examples'
Requires-Dist: pipecat-ai[elevenlabs,openai,silero]>=0.0.99; extra == 'examples'
Requires-Dist: pyaudio>=0.2.14; extra == 'examples'
Requires-Dist: python-dotenv>=1.0; extra == 'examples'
